trello_full_backup/__init__.py
trello_full_backup/backup.py
trello_full_backup-0.3.1.dist-info/LICENSE
trello_full_backup-0.3.1.dist-info/METADATA
trello_full_backup-0.3.1.dist-info/WHEEL
trello_full_backup-0.3.1.dist-info/entry_points.txt
trello_full_backup-0.3.1.dist-info/top_level.txt
trello_full_backup-0.3.1.dist-info/RECORD
