Metadata-Version: 2.1
Name: trello-full-backup
Version: 0.3.1
Summary: Backup everything from Trello
Home-page: https://github.com/jtpio/trello-full-backup
Author: Jeremy Tuloup
Author-email: jerem@jtp.io
License: MIT
Platform: UNKNOWN
Classifier: Topic :: System :: Archiving :: Backup
Classifier: Programming Language :: Python :: 3.4
Classifier: Programming Language :: Python :: 3.5
Classifier: Programming Language :: Python :: 3.6
Requires-Python: >=3.4
Requires-Dist: requests
